mphot/__init__.py
mphot/core.py
mphot/datafiles/pre_grid_03_to_3_microns_2400m_flux.pkl
mphot/datafiles/pre_grid_03_to_3_microns_2400m_radiance.pkl
mphot/datafiles/vega_03_to_3_microns.csv
mphot/datafiles/flux_calibration/gaia_bp.csv
mphot/datafiles/flux_calibration/gaia_g.csv
mphot/datafiles/flux_calibration/gaia_rp.csv
mphot/datafiles/flux_calibration/inverse_atmosphere_paranal.csv
mphot/datafiles/system_responses/.gitignore
mphot/datafiles/system_responses/gaia_bp_inverse_atmosphere_paranal_instrument_system_response.csv
mphot/datafiles/system_responses/gaia_g_inverse_atmosphere_paranal_instrument_system_response.csv
mphot/datafiles/system_responses/gaia_rp_inverse_atmosphere_paranal_instrument_system_response.csv
mphot/grids/.gitignore
mphot/grids/gaia_bp_inverse_atmosphere_paranal_precisionGrid_flux_coords.npy
mphot/grids/gaia_bp_inverse_atmosphere_paranal_precisionGrid_flux_data.npy
mphot/grids/gaia_bp_inverse_atmosphere_paranal_precisionGrid_radiance_coords.npy
mphot/grids/gaia_bp_inverse_atmosphere_paranal_precisionGrid_radiance_data.npy
mphot/grids/gaia_g_inverse_atmosphere_paranal_precisionGrid_flux_coords.npy
mphot/grids/gaia_g_inverse_atmosphere_paranal_precisionGrid_flux_data.npy
mphot/grids/gaia_g_inverse_atmosphere_paranal_precisionGrid_radiance_coords.npy
mphot/grids/gaia_g_inverse_atmosphere_paranal_precisionGrid_radiance_data.npy
mphot/grids/gaia_rp_inverse_atmosphere_paranal_precisionGrid_flux_coords.npy
mphot/grids/gaia_rp_inverse_atmosphere_paranal_precisionGrid_flux_data.npy
mphot/grids/gaia_rp_inverse_atmosphere_paranal_precisionGrid_radiance_coords.npy
mphot/grids/gaia_rp_inverse_atmosphere_paranal_precisionGrid_radiance_data.npy
mphot-1.2.3.dist-info/METADATA
mphot-1.2.3.dist-info/WHEEL
mphot-1.2.3.dist-info/licenses/LICENSE
mphot-1.2.3.dist-info/RECORD
