Metadata-Version: 2.4
Name: mphot
Version: 1.2.3
Project-URL: Documentation, https://mphot.readthedocs.io
Project-URL: Repository, https://github.com/ppp-one/mphot
Author: Peter Pedersen
License: MIT License
License-File: LICENSE
Requires-Python: >=3.11
Requires-Dist: astroquery
Requires-Dist: ipython
Requires-Dist: matplotlib
Requires-Dist: numpy
Requires-Dist: pandas
Requires-Dist: scipy
Provides-Extra: dev
Requires-Dist: black; extra == 'dev'
Requires-Dist: pytest; extra == 'dev'
Provides-Extra: docs
Requires-Dist: docformatter[tomli]; extra == 'docs'
Requires-Dist: ipywidgets; extra == 'docs'
Requires-Dist: matplotlib; extra == 'docs'
Requires-Dist: myst-nb; extra == 'docs'
Requires-Dist: sphinx; extra == 'docs'
Requires-Dist: sphinx-book-theme; extra == 'docs'
Requires-Dist: sphinx-copybutton; extra == 'docs'
Requires-Dist: sphinx-design; extra == 'docs'
Requires-Dist: toml; extra == 'docs'
Provides-Extra: test
Requires-Dist: pytest; extra == 'test'
